frst_auth_cli/__init__.py
frst_auth_cli/app.py
frst_auth_cli/caching.py
frst_auth_cli/cli.py
frst_auth_cli/company.py
frst_auth_cli/config.py
frst_auth_cli/core.py
frst_auth_cli/exceptions.py
frst_auth_cli/group.py
frst_auth_cli/user.py
frst_auth_cli-1.0.1.dist-info/METADATA
frst_auth_cli-1.0.1.dist-info/WHEEL
frst_auth_cli-1.0.1.dist-info/entry_points.txt
frst_auth_cli-1.0.1.dist-info/top_level.txt
frst_auth_cli-1.0.1.dist-info/RECORD
