Metadata-Version: 2.4
Name: frst-auth-cli
Version: 1.0.1
Summary: CLI to manage and verify user and app permissions on the FRST platform.
Home-page: https://github.com/FRST-Falconi/frst-auth-cli
Author: Marcos William Ferretti
Author-email: ferretti.spo@gmail.com
License: MIT
Classifier: Programming Language :: Python :: 3
Classifier: Operating System :: OS Independent
Classifier: Intended Audience :: Developers
Classifier: License :: OSI Approved :: MIT License
Classifier: Topic :: Software Development :: Libraries :: Application Frameworks
Classifier: Topic :: Security
Classifier: Topic :: Utilities
Requires-Python: >=3.10
Requires-Dist: typer>=0.12.0
Requires-Dist: requests>=2.25.0
Dynamic: author
Dynamic: author-email
Dynamic: classifier
Dynamic: description
Dynamic: description-content-type
Dynamic: home-page
Dynamic: license
Dynamic: requires-dist
Dynamic: requires-python
Dynamic: summary
